dtype_filters/__init__.py
dtype_filters/dtype_filters.py
dtype_filters/word_frequency.py
dtype_filters-0.0.5.dist-info/LICENCE.txt
dtype_filters-0.0.5.dist-info/METADATA
dtype_filters-0.0.5.dist-info/WHEEL
dtype_filters-0.0.5.dist-info/top_level.txt
dtype_filters-0.0.5.dist-info/RECORD
