Metadata-Version: 2.1
Name: dtype-filters
Version: 0.0.5
Summary: This pakcage is for testing purposes
Author: AWAIS NAYYAR
Author-email: awaisnayyar01@gmail.com
Classifier: Programming Language :: Python :: 3
Classifier: License :: OSI Approved :: MIT License
Classifier: Operating System :: OS Independent
License-File: LICENCE.txt
